MANIFEST.in
README.md
setup.py
binlogexplorer/__init__.py
binlogexplorer/binlog_analyser.py
binlogexplorer/binlog_parser.py
binlogexplorer/schema_parser.py
binlogexplorer/version
binlogexplorer/webui.py
binlogexplorer/static/Chart.PieceLabel.min.js
binlogexplorer/static/Chart.bundle.min.js
binlogexplorer/static/app.js
binlogexplorer/static/details_close.png
binlogexplorer/static/details_open.png
binlogexplorer/static/distinct-colors.min.js
binlogexplorer/static/jquery-1.12.4.min.js
binlogexplorer/static/jquery.dataTables.min.css
binlogexplorer/static/jquery.dataTables.min.js
binlogexplorer/static/sort_asc.png
binlogexplorer/static/sort_both.png
binlogexplorer/static/sort_desc.png
binlogexplorer/template/main.tpl
mysql_binlog_explorer.egg-info/PKG-INFO
mysql_binlog_explorer.egg-info/SOURCES.txt
mysql_binlog_explorer.egg-info/dependency_links.txt
mysql_binlog_explorer.egg-info/entry_points.txt
mysql_binlog_explorer.egg-info/not-zip-safe
mysql_binlog_explorer.egg-info/requires.txt
mysql_binlog_explorer.egg-info/top_level.txt