Metadata-Version: 2.1
Name: mysql-binlog-explorer
Version: 0.2.1
Summary: Web UI to Explore MySQL's binlog files a little easier.
Home-page: https://github.com/meuspedidos/mysql-binlog-explorer
Author: MeusPedidos Engineering Team
Author-email: israel.bgf@gmail.com, jorge.klemm@hotmail.com, cleberben.warmling@gmail.com
License: MIT
Keywords: mysql binlog analysis ui web explore
Platform: UNKNOWN
